BSMRes-1.0.2.data/data/LICENSE.txt
BSMRes-1.0.2.data/data/MANIFEST.in
BSMRes-1.0.2.data/data/README.txt
Task/Acqusition Transfer.cmd
Task/Coherence Averaging.py
Task/Coherence Processing.py
Task/Coherence Row Removal.py
Task/Coherence and Headplot - not significance.py
Task/Concat.py
Task/Copy Calibration Score.py
Task/Copy Participant Statistics.py
Task/Copy Reaction Time.py
Task/Copy Statistical Analyses.py
Task/EEG Data Transfer.cmd
Task/EEG Headplot.py
Task/EEG Line Removal.py
Task/EEG Post Processing.py
Task/Pie charts - Behavioural Data.py
Task/ROI Coherence Plot 2.py
Task/ROI Coherence Plot.py
Task/ROI Headmap 2.png
Task/ROI Headmap.png
Task/ROI Plot.py
Task/ROI Power Plot.py
Task/Trial Trigger Codes.psyexp
Task/eeg output.py
BSMRes-1.0.2.dist-info/LICENSE.txt
BSMRes-1.0.2.dist-info/METADATA
BSMRes-1.0.2.dist-info/WHEEL
BSMRes-1.0.2.dist-info/entry_points.txt
BSMRes-1.0.2.dist-info/top_level.txt
BSMRes-1.0.2.dist-info/RECORD
