Metadata-Version: 2.1
Name: BSMRes
Version: 1.0.2
Summary: Welcome to my MRes task exploring Goal Conflict using the Reinforcement Sensitivity Theory. 
Classifier: Programming Language :: Python :: 3
Classifier: License :: OSI Approved
Classifier: Operating System :: OS Independent
License-File: LICENSE.txt
Requires-Dist: pyxid2
Requires-Dist: sendgrid
Requires-Dist: plyer
Requires-Dist: pygame
Requires-Dist: pandas
Requires-Dist: google-auth
Requires-Dist: google-auth-oauthlib
Requires-Dist: google-auth-httplib2
Requires-Dist: google-api-python-client
Requires-Dist: Pillow
Requires-Dist: Scipy
Requires-Dist: Numpy
